{
  "collapse-filter": false,
  "search": "-path:zzztemplates -path:zzzimages -path:\"Player Characters\" -path:\"Session Notes\"  ",
  "showTags": false,
  "showAttachments": false,
  "hideUnresolved": false,
  "showOrphans": true,
  "collapse-color-groups": false,
  "colorGroups": [
    {
      "query": "path:General  ",
      "color": {
        "a": 1,
        "rgb": 2247660
      }
    },
    {
      "query": "path:Locations  ",
      "color": {
        "a": 1,
        "rgb": 14625322
      }
    },
    {
      "query": "path:NPCs  ",
      "color": {
        "a": 1,
        "rgb": 2023450
      }
    },
    {
      "query": "path:Quests",
      "color": {
        "a": 1,
        "rgb": 15400775
      }
    }
  ],
  "collapse-display": false,
  "showArrow": false,
  "textFadeMultiplier": 0,
  "nodeSizeMultiplier": 1,
  "lineSizeMultiplier": 1,
  "collapse-forces": true,
  "centerStrength": 0.518713248970312,
  "repelStrength": 10,
  "linkStrength": 1,
  "linkDistance": 250,
  "scale": 0.7766780967903398,
  "close": true
}